isPowerOfTwo/__init__.py
isPowerOfTwo/isPowerOfTwo.py
isPowerOfTwo-1.0.0.dist-info/LICENSE
isPowerOfTwo-1.0.0.dist-info/METADATA
isPowerOfTwo-1.0.0.dist-info/WHEEL
isPowerOfTwo-1.0.0.dist-info/top_level.txt
isPowerOfTwo-1.0.0.dist-info/RECORD
